{
  "brand": {
    "name": "Abbott Engage",
    "subtitle": "Retailer Reward Payouts",
    "fullName": "Abbott Engage -- ShakePe"
  },
  "colors": {
    "blue": "#159BD7",
    "blueLight": "#E6F4FA",
    "blueDark": "#0D7AB0",
    "darkBlue": "#001751",
    "paleBlue": "#F2F3F6",
    "white": "#FFFFFF",
    "grey": "#D9D9D9",
    "darkGrey": "#777777",
    "textPrimary": "#1F2937",
    "textSecondary": "#6B7280",
    "success": "#10B981",
    "successLight": "#D1FAE5",
    "successDark": "#059669",
    "warning": "#F59E0B",
    "warningLight": "#FEF3C7",
    "error": "#EF4444",
    "errorLight": "#FEE2E2",
    "purple": "#8B5CF6",
    "purpleLight": "#EDE9FE",
    "teal": "#14B8A6",
    "pink": "#EC4899"
  },
  "typography": {
    "fontFamily": "'Inter', sans-serif",
    "headingFamily": "'Kanit', sans-serif",
    "fontUrl": "https://fonts.googleapis.com/css2?family=Kanit:wght@600;700;800&family=Inter:wght@400;500;600;700&display=swap"
  },
  "logo": {
    "svg": "<g transform=\"translate(-635.84274,-750.91924)\"><path fill=\"#3BB5E8\" d=\"m 708.91763,751.91925 h -72.07462 v 11.07625 h 68.47655 v 0.01 c 1.98226,0 3.565,1.58961 3.565,3.56314 v 37.19433 l -0.009,0.0315 c -0.0122,1.96479 -1.61079,3.54383 -3.57188,3.54383 h -53.81334 c -1.97009,0 -3.58246,-1.59174 -3.58246,-3.57558 v -15.02596 c 0,-1.97352 1.61237,-3.57557 3.58246,-3.57557 h 46.29759 v -11.06144 h -49.90121 c -6.09944,0 -11.04398,4.93554 -11.04398,11.03074 v 22.23903 c 0,6.09944 4.94454,11.04212 11.04398,11.04212 h 61.03064 c 6.10473,0 11.04212,-4.94268 11.04212,-11.04212 v -44.40449 c 0,-6.09865 -4.93739,-11.04556 -11.04212,-11.04556\"/></g>",
    "viewBox": "-5 -5 92 78"
  },
  "nav": [
    { "label": "Dashboard", "href": "/01-dashboard.html", "icon": "dashboard" },
    { "label": "Retailer Onboarding", "href": "/02-retailer-onboarding.html", "icon": "how_to_reg" },
    { "type": "divider" },
    { "label": "Payout Batches", "href": "/03-payout-batches.html", "icon": "payments" },
    { "label": "Batch Detail", "href": "/04-batch-detail.html", "icon": "receipt_long" },
    { "label": "Wallet", "href": "/05-wallet.html", "icon": "account_balance_wallet" },
    { "type": "divider" },
    { "label": "TDS Reports", "href": "/06-tds-reports.html", "icon": "summarize" },
    { "label": "Manual Review", "href": "/07-manual-review.html", "icon": "rate_review", "badge": "12" },
    { "type": "divider" },
    { "label": "Settings", "href": "/08-settings.html", "icon": "settings" },
    { "type": "divider" },
    { "label": "Retailer Wizard", "href": "/09-retailer-wizard.html", "icon": "phonelink_setup" }
  ]
}
